Workbook
Name OLE_LINK1: 'ejercicio 1'!$G$4
Name OLE_LINK1: 'ejercicio 2'!$G$4

Sheet ejercicio 1
F2: Ejercicio práctico: una empresa fabrica y comercializa productos de consumo masivo. Con la información que aparece a continuación se debe construir el estado de costo del producto manufacturado y vendido y el estado de resultado.
F6: Descripción | G6: valor
F7: Precio unitario | G7: 8
F8: Inventario final de productos en proceso | G8: 13000
F9: Inventario final de materiales directo | G9: 13000
F10: Inventario inicial de productos en proceso | G10: 14000
F11: Inventario inicial de materiales directo | G11: 15000
F12: Mano de obra indirecta | G12: 80000
F13: Gastos de administración | G13: 48000
F14: Gasto de venta | G14: 125000
F15: Mano de obra directa | G15: 75000
F16: Inventario final de productos terminado | G16: 90000
F17: Unidades vendidas | G17: 130000
F18: impuesto | G18: 0.3
... F22: Inventario inicial de productos terminado | G22: 80000

Sheet solucion 1
F1: Descripción | G1: valor
F2: Costos de materiales directos
F3: costo del inventario inicial de materiales directos | G3: ='ejercicio 1'!G11 -> 15000
F4: + compras de materiales directo | G4: ='ejercicio 1'!G19 -> 138000
F5: costos de materiales directos disponible para su uso | G5: =G3+G4 -> 153000
F6: - costo inventario final de materiales directos | G6: ='ejercicio 1'!G9 -> 13000
F7: costos de materiales directo usados | G7: =G5-G6 -> 140000
F8: Mano de obra directa | G8: ='ejercicio 1'!G15 -> 75000
F9: Costos indirecto de fabricación CIF
F10: Materiales indirectos | G10: ='ejercicio 1'!G20 -> 1500
F11: Mano de obra indirecta | G11: ='ejercicio 1'!G12 -> 80000
F12: Otros costos indirectos de fabricación | G12: ='ejercicio 1'!G21 -> 41000
F13: costos indirecto de fabricación CIF | G13: =SUM(G10:G12) -> 122500
F14: costo de producción | G14: =G7+G8+G13 -> 337500
F15: + inventario inicial de productos en proceso | G15: ='ejercicio 1'!G10 -> 14000
F16: costos de producción en procesos | G16: =G14+G15 -> 351500
F17: - inventario final de productos en proceso | G17: ='ejercicio 1'!G8 -> 13000
F18: costos de productos manufacturados | G18: =G16-'ejercicio 1'!G8 -> 338500
F19: + inventario inicial de productos terminado | G19: ='ejercicio 1'!G22 -> 80000
F20: costo de producto disponible para la venta | G20: =G18+G19 -> 418500
F21: - inventario final de productos terminado | G21: ='ejercicio 1'!G16 -> 90000
F22: costo de productos manufacturados y vendidos (CMV) | G22: =G20-G21 -> 328500
F24: Venta | G24: ='ejercicio 1'!G17*'ejercicio 1'!G7 -> 1040000
F25: costo de productos manufacturados y vendidos (CMV) | G25: =G22 -> 328500
F26: Utilidad bruta | G26: =G24-G25 -> 711500
F27: (-) gasto de administración | G27: ='ejercicio 1'!G13 -> 48000
F28: (-) gasto venta | G28: ='ejercicio 1'!G14 -> 125000
F29: Utilidad operacional | G29: =G26-G27-G28 -> 538500
F30: (-) impuesto 30% | G30: =G29*'ejercicio 1'!G18 -> 161550
F31: Utilidad neta | G31: =G29-G30 -> 376950

Sheet ejercicio 2
F2: Ejercicio 2: una empresa fabrica y comercializa bolsos. Con la información que aparece a continuación se debe construir el estado de costo del producto manufacturado y vendido y el estado de resultado
F6: Descripción | G6: valor
F7: Precio unitario | G7: 5
F8: Inventario final de productos en proceso | G8: 18000
F9: Inventario final de materiales directo | G9: 16000
F10: Inventario inicial de productos en proceso | G10: 10000
F11: Inventario inicial de materiales directo | G11: 12000
F12: Mano de obra indirecta | G12: 110000
F13: Gastos de administración | G13: 20000
F14: Gasto de venta | G14: 78000
F15: Mano de obra directa | G15: 90000
F16: Inventario final de productos terminado | G16: 100000
F17: Unidades vendidas | G17: 150000
F18: impuesto | G18: 0.3
... F22: Inventario inicial de productos terminado | G22: 66000

Sheet solucion 2
F1: Descripción | G1: valor
F2: Costos de materiales directos
F3: costo del inventario inicial de materiales directos | G3: ='ejercicio 2'!G11 -> 12000
F4: + compras de materiales directo | G4: ='ejercicio 2'!G19 -> 145000
F5: costos de materiales directos disponible para su uso | G5: =G3+G4 -> 157000
F6: - costo inventario final de materiales directos | G6: ='ejercicio 2'!G9 -> 16000
F7: costos de materiales directo usados | G7: =G5-G6 -> 141000
F8: Mano de obra directa | G8: ='ejercicio 2'!G15 -> 90000
F9: Costos indirecto de fabricación CIF
F10: Materiales indirectos | G10: ='ejercicio 2'!G20 -> 8000
F11: Mano de obra indirecta | G11: ='ejercicio 2'!G12 -> 110000
F12: Otros costos indirectos de fabricación | G12: ='ejercicio 2'!G21 -> 40000
F13: costos indirecto de fabricación CIF | G13: =SUM(G10+G11+G12) -> 158000
F14: costo de producción | G14: =G7+G8+G13 -> 389000
F15: + inventario inicial de productos en proceso | G15: ='ejercicio 2'!G10 -> 10000
F16: costos de producción en procesos | G16: =G14+G15 -> 399000
F17: - inventario final de productos en proceso | G17: ='ejercicio 2'!G8 -> 18000
F18: costos de productos manufacturados | G18: =G16-G17 -> 381000
F19: + inventario inicial de productos terminado | G19: ='ejercicio 2'!G22 -> 66000
F20: costo de producto disponible para la venta | G20: =G18+G19 -> 447000
F21: - inventario final de productos terminado | G21: ='ejercicio 2'!G16 -> 100000
F22: costo de productos manufacturados y vendidos (CMV) | G22: =G20-G21 -> 347000
F24: Venta | G24: ='ejercicio 2'!G17*'ejercicio 2'!G7 -> 750000
F25: costo de productos manufacturados y vendidos (CMV) | G25: =G22 -> 347000
F26: Utilidad bruta | G26: =G24-G25 -> 403000
F27: (-) gasto de administración | G27: ='ejercicio 2'!G13 -> 20000
F28: (-) gasto venta | G28: ='ejercicio 2'!G14 -> 78000
F29: Utilidad operacional | G29: =G26-G27-G28 -> 305000
F30: (-) impuesto 30% | G30: =G29*'ejercicio 2'!G18 -> 91500
F31: Utilidad neta | G31: =G29-G30 -> 213500
